smart_pdf_for_business/__init__.py
smart_pdf_for_business/pdf_doc.py
smart_pdf_for_business/pdf_doc_batch.py
smart_pdf_for_business/signature_detector.py
smart_pdf_for_business/utils.py
smart_pdf_for_business-1.0.0.dist-info/METADATA
smart_pdf_for_business-1.0.0.dist-info/WHEEL
smart_pdf_for_business-1.0.0.dist-info/licenses/LICENSE
smart_pdf_for_business-1.0.0.dist-info/RECORD
