Metadata-Version: 2.4
Name: smart_pdf_for_business
Version: 1.0.0
Summary: A Python library for business PDF related content analysis
Project-URL: Homepage, https://github.com/Sagraetor/Smart-Pdf-for-Business
Author-email: Sagraetor <sagraetor@gmail.com>
License-Expression: MIT
License-File: LICENSE
Keywords: Ai,Business automation,Data extraction,Document parsing,Machine Learning,NLP,OCR,PDF,PDF analysis,Semantic search,Signatures,Text extraction
Classifier: Operating System :: OS Independent
Classifier: Programming Language :: Python :: 3
Classifier: Topic :: Software Development :: Libraries :: Python Modules
Classifier: Topic :: Text Processing
Classifier: Topic :: Text Processing :: Filters
Requires-Python: >=3.10
Requires-Dist: accelerate==1.11.0
Requires-Dist: annotated-types==0.7.0
Requires-Dist: antlr4-python3-runtime==4.9.3
Requires-Dist: attrs==25.4.0
Requires-Dist: beautifulsoup4==4.14.2
Requires-Dist: blis==1.3.0
Requires-Dist: catalogue==2.0.10
Requires-Dist: certifi==2025.11.12
Requires-Dist: charset-normalizer==3.4.4
Requires-Dist: click==8.3.0
Requires-Dist: cloudpathlib==0.23.0
Requires-Dist: colorama==0.4.6
Requires-Dist: coloredlogs==15.0.1
Requires-Dist: colorlog==6.10.1
Requires-Dist: confection==0.1.5
Requires-Dist: cymem==2.0.11
Requires-Dist: dill==0.4.0
Requires-Dist: docling-core==2.50.1
Requires-Dist: docling-ibm-models==3.10.2
Requires-Dist: docling-parse==4.7.1
Requires-Dist: docling==2.61.2
Requires-Dist: easyocr==1.7.2
Requires-Dist: et-xmlfile==2.0.0
Requires-Dist: faker==38.0.0
Requires-Dist: filelock==3.20.0
Requires-Dist: filetype==1.2.0
Requires-Dist: flatbuffers==25.9.23
Requires-Dist: fsspec==2025.10.0
Requires-Dist: huggingface-hub==0.36.0
Requires-Dist: humanfriendly==10.0
Requires-Dist: idna==3.11
Requires-Dist: imageio==2.37.2
Requires-Dist: jinja2==3.1.6
Requires-Dist: joblib==1.5.2
Requires-Dist: jsonlines==4.0.0
Requires-Dist: jsonref==1.1.0
Requires-Dist: jsonschema-specifications==2025.9.1
Requires-Dist: jsonschema==4.25.1
Requires-Dist: latex2mathml==3.78.1
Requires-Dist: lazy-loader==0.4
Requires-Dist: lxml==6.0.2
Requires-Dist: markdown-it-py==4.0.0
Requires-Dist: marko==2.2.1
Requires-Dist: markupsafe==3.0.3
Requires-Dist: mdurl==0.1.2
Requires-Dist: mpire==2.10.2
Requires-Dist: mpmath==1.3.0
Requires-Dist: multiprocess==0.70.18
Requires-Dist: murmurhash==1.0.13
Requires-Dist: networkx==3.5
Requires-Dist: ninja==1.13.0
Requires-Dist: numpy==2.2.6
Requires-Dist: omegaconf==2.3.0
Requires-Dist: onnxruntime==1.23.2
Requires-Dist: opencv-python-headless==4.12.0.88
Requires-Dist: opencv-python==4.12.0.88
Requires-Dist: openpyxl==3.1.5
Requires-Dist: packaging==25.0
Requires-Dist: pandas==2.3.3
Requires-Dist: pillow==11.3.0
Requires-Dist: pluggy==1.6.0
Requires-Dist: polyfactory==2.22.4
Requires-Dist: preshed==3.0.10
Requires-Dist: protobuf==6.33.1
Requires-Dist: psutil==7.1.3
Requires-Dist: pyclipper==1.3.0.post6
Requires-Dist: pydantic-core==2.41.5
Requires-Dist: pydantic-settings==2.12.0
Requires-Dist: pydantic==2.12.4
Requires-Dist: pygments==2.19.2
Requires-Dist: pylatexenc==2.10
Requires-Dist: pymupdf==1.26.6
Requires-Dist: pypdfium2==4.30.0
Requires-Dist: pyreadline3==3.5.4
Requires-Dist: python-bidi==0.6.7
Requires-Dist: python-dateutil==2.9.0.post0
Requires-Dist: python-docx==1.2.0
Requires-Dist: python-dotenv==1.2.1
Requires-Dist: python-pptx==1.0.2
Requires-Dist: pytz==2025.2
Requires-Dist: pywin32==311
Requires-Dist: pyyaml==6.0.3
Requires-Dist: rapidocr==3.4.2
Requires-Dist: referencing==0.37.0
Requires-Dist: regex==2025.11.3
Requires-Dist: requests==2.32.5
Requires-Dist: rich==14.2.0
Requires-Dist: rpds-py==0.28.0
Requires-Dist: rtree==1.4.1
Requires-Dist: safetensors==0.6.2
Requires-Dist: scikit-image==0.25.2
Requires-Dist: scikit-learn==1.7.2
Requires-Dist: scipy==1.16.3
Requires-Dist: semchunk==2.2.2
Requires-Dist: sentence-transformers==5.1.2
Requires-Dist: setuptools==80.9.0
Requires-Dist: shapely==2.1.2
Requires-Dist: shellingham==1.5.4
Requires-Dist: six==1.17.0
Requires-Dist: smart-open==7.5.0
Requires-Dist: soupsieve==2.8
Requires-Dist: spacy-layout==0.0.12
Requires-Dist: spacy-legacy==3.0.12
Requires-Dist: spacy-loggers==1.0.5
Requires-Dist: spacy==3.8.8
Requires-Dist: srsly==2.5.1
Requires-Dist: sympy==1.14.0
Requires-Dist: tabulate==0.9.0
Requires-Dist: thinc==8.3.8
Requires-Dist: threadpoolctl==3.6.0
Requires-Dist: tifffile==2025.10.16
Requires-Dist: tokenizers==0.22.1
Requires-Dist: torch==2.9.0
Requires-Dist: torchvision==0.24.0
Requires-Dist: tqdm==4.67.1
Requires-Dist: transformers==4.57.1
Requires-Dist: typer-slim==0.20.0
Requires-Dist: typer==0.19.2
Requires-Dist: typing-extensions==4.15.0
Requires-Dist: typing-inspection==0.4.2
Requires-Dist: tzdata==2025.2
Requires-Dist: urllib3==2.5.0
Requires-Dist: wasabi==1.1.3
Requires-Dist: weasel==0.4.2
Requires-Dist: wrapt==2.0.1
Requires-Dist: xlsxwriter==3.2.9
